random_pesel/__init__.py
random_pesel/random_pesel.py
random_pesel-1.0.dist-info/LICENCE
random_pesel-1.0.dist-info/METADATA
random_pesel-1.0.dist-info/WHEEL
random_pesel-1.0.dist-info/top_level.txt
random_pesel-1.0.dist-info/RECORD
